<?xml version="1.0" encoding="utf-8" ?>
<Defs>

  <!-- Issue -->

  <IssueDef>
    <defName>WorkTableWorkSpeedFactorPercept</defName>
    <label>WorkTableWorkSpeedFactor</label>
    <iconPath>UI/Issues/WorkTableWorkSpeedFactorPercept</iconPath>
  </IssueDef>

  <!-- Precepts -->

  <PreceptDef>
    <defName>WorkTableWorkSpeedFactor_ExtremelySlow</defName>
    <issue>WorkTableWorkSpeedFactorPercept</issue>
    <label>extremely slow</label>
    <description>Research isn't a worthwhile activity at all. Why try hard at it?</description>
    <impact>High</impact>
    <displayOrderInIssue>50</displayOrderInIssue>
    <displayOrderInImpact>1000</displayOrderInImpact>
    <statOffsets>
      <WorkTableWorkSpeedFactor>-0.5</WorkTableWorkSpeedFactor>
      <AssemblySpeedFactor>-0.5</AssemblySpeedFactor>
    </statOffsets>
  </PreceptDef>

  <PreceptDef>
    <defName>WorkTableWorkSpeedFactor_VerySlow</defName>
    <issue>WorkTableWorkSpeedFactorPercept</issue>
    <label>very Slow</label>
    <description>Research work is unworthy of serious respect. Better not to be seen trying hard at it.</description>
    <impact>High</impact>
    <displayOrderInIssue>40</displayOrderInIssue>
    <displayOrderInImpact>1000</displayOrderInImpact>
    <statOffsets>
      <WorkTableWorkSpeedFactor>-0.35</WorkTableWorkSpeedFactor>
      <AssemblySpeedFactor>-0.35</AssemblySpeedFactor>
    </statOffsets>
  </PreceptDef>

  <PreceptDef>
    <defName>WorkTableWorkSpeedFactor_Slow</defName>
    <issue>WorkTableWorkSpeedFactorPercept</issue>
    <label>Slow</label>
    <description>Research work just isn't particularly meaningful. Why try hard at it?</description>
    <impact>Medium</impact>
    <displayOrderInIssue>30</displayOrderInIssue>
    <displayOrderInImpact>1000</displayOrderInImpact>
    <statOffsets>
      <WorkTableWorkSpeedFactor>-0.1</WorkTableWorkSpeedFactor>
      <AssemblySpeedFactor>-0.1</AssemblySpeedFactor>
    </statOffsets>
  </PreceptDef>

  <PreceptDef>
    <defName>WorkTableWorkSpeedFactor_Normal</defName>
    <issue>WorkTableWorkSpeedFactorPercept</issue>
    <label>normal</label>
    <description>Research is a worthwhile form of work that the community needs.</description>
    <impact>Low</impact>
    <displayOrderInIssue>10</displayOrderInIssue>
    <defaultSelectionWeight>1</defaultSelectionWeight>
  </PreceptDef>

  <PreceptDef>
    <defName>WorkTableWorkSpeedFactor_Fast</defName>
    <issue>WorkTableWorkSpeedFactorPercept</issue>
    <label>fast</label>
    <description>Research is an especially virtuous activity.</description>
    <impact>Low</impact>
    <displayOrderInIssue>10</displayOrderInIssue>
    <displayOrderInImpact>1000</displayOrderInImpact>
    <statOffsets>
      <WorkTableWorkSpeedFactor>0.1</WorkTableWorkSpeedFactor>
      <AssemblySpeedFactor>0.1</AssemblySpeedFactor>
    </statOffsets>
  </PreceptDef>

  <PreceptDef>
    <defName>WorkTableWorkSpeedFactor_VeryFast</defName>
    <issue>WorkTableWorkSpeedFactorPercept</issue>
    <label>very fast</label>
    <description>Research is among the most meaningful acts a person can perform.</description>
    <impact>Medium</impact>
    <displayOrderInIssue>0</displayOrderInIssue>
    <displayOrderInImpact>1000</displayOrderInImpact>
    <statOffsets>
      <WorkTableWorkSpeedFactor>0.3</WorkTableWorkSpeedFactor>
      <AssemblySpeedFactor>0.3</AssemblySpeedFactor>
    </statOffsets>
  </PreceptDef>

  <PreceptDef>
    <defName>WorkTableWorkSpeedFactor_ExtremelyFast</defName>
    <issue>WorkTableWorkSpeedFactorPercept</issue>
    <label>extremely fast</label>
    <description>Research is among the most meaningful acts a person can perform.</description>
    <impact>Medium</impact>
    <displayOrderInIssue>0</displayOrderInIssue>
    <displayOrderInImpact>1000</displayOrderInImpact>
    <statOffsets>
      <WorkTableWorkSpeedFactor>0.5</WorkTableWorkSpeedFactor>
      <AssemblySpeedFactor>0.5</AssemblySpeedFactor>
    </statOffsets>
  </PreceptDef>

</Defs>
